setup.py
samur/Mainboard.py
samur/__init__.py
samur.egg-info/PKG-INFO
samur.egg-info/SOURCES.txt
samur.egg-info/dependency_links.txt
samur.egg-info/requires.txt
samur.egg-info/top_level.txt
samur/devices/AnalogModule.py
samur/devices/DigitalModule.py
samur/devices/Multiplexer.py
samur/devices/ShiftRegister.py
samur/devices/__init__.py