Metadata-Version: 1.0
Name: samur
Version: 0.3.0
Summary: Samur MainBoard Python Module
Home-page: https://github.com/ivmech/samur
Author: Caner Durmusoglu
Author-email: cnr437@gmail.com
License: UNKNOWN
Platform: UNKNOWN
